pipetint/__init__.py
pipetint/cli.py
pipetint/color_codes.py
pipetint/colors.py
pipetint/core.py
pipetint/enhanced.py
pipetint-2.1.1.dist-info/LICENSE
pipetint-2.1.1.dist-info/METADATA
pipetint-2.1.1.dist-info/WHEEL
pipetint-2.1.1.dist-info/entry_points.txt
pipetint-2.1.1.dist-info/RECORD
